{
  "type": "FeatureCollection",
  "features": [
    {
      "type": "Feature",
      "geometry": {
        "type": "Point",
        "coordinates": [
          -122.468281976832,
          37.8726680659785
        ]
      },
      "properties": {
        "permit_year": 2017,
        "permit_address": "5 CREST RD",
        "permit_units": 1,
        "permit_category": "SU"
      }
    },
    {
      "type": "Feature",
      "geometry": {
        "type": "Point",
        "coordinates": [
          -122.470510836806,
          37.8763907232533
        ]
      },
      "properties": {
        "permit_year": 2017,
        "permit_address": "11 BAY VIEW AVE",
        "permit_units": 1,
        "permit_category": "SU"
      }
    },
    {
      "type": "Feature",
      "geometry": {
        "type": "Point",
        "coordinates": [
          -118.169238,
          34.040568
        ]
      },
      "properties": {
        "permit_year": 2016,
        "permit_address": "Unidentified",
        "permit_units": 0,
        "permit_category": "Unidentified"
      }
    },
    {
      "type": "Feature",
      "geometry": {
        "type": "Point",
        "coordinates": [
          -118.169238,
          34.040568
        ]
      },
      "properties": {
        "permit_year": 2015,
        "permit_address": "Unidentified",
        "permit_units": 0,
        "permit_category": "Unidentified"
      }
    },
    {
      "type": "Feature",
      "geometry": {
        "type": "Point",
        "coordinates": [
          -118.169238,
          34.040568
        ]
      },
      "properties": {
        "permit_year": 2014,
        "permit_address": "Unidentified",
        "permit_units": 0,
        "permit_category": "Unidentified"
      }
    },
    {
      "type": "Feature",
      "geometry": {
        "type": "Point",
        "coordinates": [
          -118.096755,
          34.15082
        ]
      },
      "properties": {
        "permit_year": 2019,
        "permit_address": "300 Bella Vista Ave",
        "permit_units": 1,
        "permit_category": "ADU"
      }
    },
    {
      "type": "Feature",
      "geometry": {
        "type": "Point",
        "coordinates": [
          -118.169238,
          34.040568
        ]
      },
      "properties": {
        "permit_year": 2019,
        "permit_address": "46 Cliff Rd",
        "permit_units": 1,
        "permit_category": "SFD"
      }
    }
  ]
}